{
  "alias": "abogado",
  "nombre": "Estudio Rossi",
  "rubro": "Abogacía",
  "profesion": "Abogado · Derecho laboral y civil",
  "tags": [
    "Laboral",
    "Civil"
  ],
  "avatar": "https://images.unsplash.com/photo-1522071820081-009f0129c71c?w=256&auto=format&q=80",
  "wa_numero": "5491144443333",
  "wa_mensaje": "Hola, necesito una consulta legal.",
  "instagram": "",
  "reservar_url": "https://cal.com/estudiorossi/consulta",
  "links": [
    {
      "label": "LinkedIn",
      "url": "https://linkedin.com/company/estudiorossi",
      "icon": "linkedin"
    },
    {
      "label": "Ubicación",
      "url": "https://maps.google.com/?q=Microcentro%20CABA",
      "icon": "maps"
    }
  ],
  "footer": "Primera orientación por WhatsApp sin cargo."
}